mkpipe_core/__init__.py
mkpipe_core/config.py
mkpipe_core/core.py
mkpipe_core/plugins/__init__.py
mkpipe_core/plugins/registry.py
mkpipe_core/utils/__init__.py
mkpipe_core/utils/logger.py
mkpipe_core-0.1.2.dist-info/LICENSE
mkpipe_core-0.1.2.dist-info/METADATA
mkpipe_core-0.1.2.dist-info/WHEEL
mkpipe_core-0.1.2.dist-info/top_level.txt
mkpipe_core-0.1.2.dist-info/RECORD
