Metadata-Version: 2.1
Name: mkpipe-core
Version: 0.1.2
Summary: Core ETL pipeline framework for mkpipe.
Author: Metin Karakus
Author-email: metin_karakus@yahoo.com
License: Apache License 2.0
Classifier: Programming Language :: Python :: 3
Classifier: License :: OSI Approved :: Apache Software License
Requires-Python: >=3.8
License-File: LICENSE
